src/__init__.py
src/municipalities_nepal.py
nepali_municipality-1.0.0.dist-info/LICENSE
nepali_municipality-1.0.0.dist-info/METADATA
nepali_municipality-1.0.0.dist-info/WHEEL
nepali_municipality-1.0.0.dist-info/top_level.txt
nepali_municipality-1.0.0.dist-info/RECORD
