Metadata-Version: 2.1
Name: nepali-municipality
Version: 1.0.0
Summary: Nepali  municipalities is a python package to get data about Nepali municipalities based on districts 
Home-page: https://github.com/nawarazpokhrel/Nepali-Municipalites
Author: Navaraj Pokharel
Author-email: navarajpokharel@outlook.com
License: UNKNOWN
Keywords: Nepali,nepali districts,nepali municipalities,navaraj pokharel,nepali states
Platform: UNKNOWN
Classifier: Programming Language :: Python :: 3
Classifier: License :: OSI Approved :: MIT License
Classifier: Operating System :: OS Independent
Requires-Python: >=3.6
License-File: LICENSE
